LICENSE
MANIFEST.in
README.md
requirements.txt
setup.py
as_rpc/__init__.py
as_rpc/base.py
as_rpc/client.py
as_rpc/handler.py
as_rpc/progress.py
as_rpc/server.py
as_rpc/utils.py
as_rpc.egg-info/PKG-INFO
as_rpc.egg-info/SOURCES.txt
as_rpc.egg-info/dependency_links.txt
as_rpc.egg-info/requires.txt
as_rpc.egg-info/top_level.txt