Metadata-Version: 2.1
Name: as-rpc
Version: 1.0.0.post4
Summary: Remote Procedure Caller (RPC) based-on Asynchronous IO and Socket
Home-page: https://github.com/bowen-xu/aio_rpc
Author: Bowen Xu
Author-email: xubowen@pku.edu.cn
License: MIT
Keywords: asyncio,rpc,socket,remote procedure call
Classifier: Development Status :: 4 - Beta
Classifier: Intended Audience :: Developers
Classifier: License :: OSI Approved :: MIT License
Classifier: Natural Language :: English
Classifier: Natural Language :: Chinese (Simplified)
Classifier: Programming Language :: Python :: 3.7
Classifier: Programming Language :: Python :: 3.8
Classifier: Programming Language :: Python :: 3.9
Classifier: Programming Language :: Python :: 3.10
Classifier: Programming Language :: Python :: 3.11
Requires-Python: >=3.7.0
License-File: LICENSE
